mkdocs_same_dir/plugin.py
mkdocs_same_dir-0.1.2.dist-info/entry_points.txt
mkdocs_same_dir-0.1.2.dist-info/LICENSE.md
mkdocs_same_dir-0.1.2.dist-info/WHEEL
mkdocs_same_dir-0.1.2.dist-info/METADATA
mkdocs_same_dir-0.1.2.dist-info/RECORD
