Metadata-Version: 2.1
Name: mkdocs-same-dir
Version: 0.1.2
Summary: MkDocs plugin to allow placing mkdocs.yml in the same directory as documentation
Home-page: https://github.com/oprypin/mkdocs-same-dir
License: MIT
Keywords: mkdocs,mkdocs-plugin
Author: Oleh Prypin
Author-email: oleh@pryp.in
Requires-Python: >=3.6,<4.0
Classifier: License :: OSI Approved :: MIT License
Classifier: Programming Language :: Python :: 3
Classifier: Programming Language :: Python :: 3.6
Classifier: Programming Language :: Python :: 3.7
Classifier: Programming Language :: Python :: 3.8
Classifier: Programming Language :: Python :: 3.9
Classifier: Programming Language :: Python :: 3.10
Requires-Dist: mkdocs (>=1.0.3,<2.0.0)
Project-URL: Repository, https://github.com/oprypin/mkdocs-same-dir
